{
  "bg": "https://i.ibb.co/8sZrfMP/background.jpg",
  "title": "Quiz Dark Souls",
  "description": "Teste os seus conhecimentos sobre Dark Souls",
  "questions": [
    {
      "image": "https://media.giphy.com/media/YleijU6Jfr0lzR708w/giphy.gif",
      "title": "Qual filha do manus representa o medo?",
      "description": "Dark Souls 2",
      "answer": 0,
      "alternatives": ["Alssana", "Elana", "Nadalia", "Nashandra"]
    },
    {
      "image": "https://media.giphy.com/media/IiBlJr6FZTtvi/giphy.gif",
      "title": "Objetivo da Way Of White",
      "description": "Dark Souls 1",
      "answer": 2,
      "alternatives": [
        "Retomar as Catacumbas de Nito",
        "Aprender todos os milagres",
        "Recuperar o Rite of Kindling",
        "Nenhuma das anteriores"
      ]
    },
    {
      "image": "https://media.giphy.com/media/kpDKiZGR6wB7pT7IVT/giphy.gif",
      "title": "O que Oceiros segura em sua mão?",
      "description": "Dark Souls 3",
      "answer": 2,
      "alternatives": [
        "Nada",
        "Um presente de sua amada",
        "Seu filho",
        "Uma espada"
      ]
    },
    {
      "image": "https://media.giphy.com/media/wK1sxPSmRntrG/giphy.gif",
      "title": "Porque o rei sem nome foi banido por seu pai?",
      "description": "Dark Souls 3",
      "answer": 3,
      "alternatives": [
        "Fez algo com um dos irmãos",
        "Planejar matar ele",
        "Planejar tomar Anor Londo",
        "Colaborar com um dragão"
      ]
    },
    {
      "image": "https://media.giphy.com/media/LLvqxmK3gOXLy/giphy.gif",
      "title": "O que Solaire está procurando durante todo o jogo?",
      "description": "Dark Souls 1",
      "answer": 1,
      "alternatives": [
        "Sua família",
        "Seu próprio sol pessoal",
        "Uma arma específica",
        "Vingança"
      ]
    },
    {
      "image": "https://media.giphy.com/media/h5REkBSNmLTP2/giphy.gif",
      "title": "Quem é o único chefe no jogo que também é um personagem invocado em uma batalha de chefe diferente?",
      "description": "Dark Souls 1",
      "answer": 3,
      "alternatives": [
        "Artorias",
        "Ornstein e Smough",
        "Manus",
        "Sif"
      ]
    },
    {
      "image": "https://media.giphy.com/media/twq99EDXbUs8BOdrTY/giphy.gif",
      "title": "Onde a águia leva o jogador após a morte do perseguidor?",
      "description": "Dark Souls 2",
      "answer": 1,
      "alternatives": [
        "Oficina do McDuff",
        "Bastilha perdida",
        "Vale da colheita",
        "Torre ads Chamas de Heide"
      ]
    },
    {
      "image": "https://media.giphy.com/media/QIhOh6VX7Tx8qQcMek/giphy.gif",
      "title": "A espada do cavaleiro de heide tem a habilidade de...",
      "description": "Dark Souls 2",
      "answer": 3,
      "alternatives": [
        "Escuridão",
        "Fogo",
        "Sangramento",
        "Raio"
      ]
    },
    {
      "image": "https://media.giphy.com/media/l49JKCSoloVTGjmWQ/giphy.gif",
      "title": "O sete do solaire em DS3 é adquirido...",
      "description": "Dark Souls 3",
      "answer": 0,
      "alternatives": [
        "No Pickle Pee",
        "Fazendo a quest do Patches",
        "Na estátua do pacto do Sol",
        "No topo de Firelink"
      ]
    },
    {
      "image": "https://media.giphy.com/media/10ARoeG4fTeeje/giphy.gif",
      "title": "Quantas classes iniciam com uma arma com dano de golpe?",
      "description": "Dark Souls 3",
      "answer": 1,
      "alternatives": [
        "6",
        "2",
        "3",
        "4"
      ]
    }
  ],
  "external": [""],
  "theme": {
    "colors": {
      "primary": "#c19d53",
      "secondary": "#c19d20",
      "mainBg": "#333333",
      "contrastText": "#FFFFFF",
      "wrong": "#FF4040",
      "success": "#4CAF50"
    },
    "borderRadius": "4px"
  }
}
